capote_ai/__init__.py
capote_ai/grammar_check.py
capote_ai/pdf_to_text.py
capote_ai/rubric_gen.py
capote_ai/viva_questions.py
tests/62_test.py
tests/__init__.py
tests/edge_case_testing.py
tests/grammar_test.py
tests/qgen_test.py
tests/rubric_gen_test.py
capote_ai-0.5.2.dist-info/METADATA
capote_ai-0.5.2.dist-info/WHEEL
capote_ai-0.5.2.dist-info/top_level.txt
capote_ai-0.5.2.dist-info/RECORD
