Metadata-Version: 2.1
Name: capote_ai
Version: 0.5.2
